Metadata-Version: 1.1
Name: sanic-ipware
Version: 0.1.0
Summary: Retrieve your client's IP address (or try its best to)
Home-page: https://github.com/vltr/sanic-ipware
Author: Richard Kuesters
Author-email: rkuesters@gmail.com
License: MIT license
Keywords: sanic,request,ip
Platform: UNKNOWN
Classifier: Development Status :: 3 - Alpha
Classifier: Intended Audience :: Developers
Classifier: License :: OSI Approved :: MIT License
Classifier: Operating System :: Unix
Classifier: Operating System :: POSIX
Classifier: Operating System :: Microsoft :: Windows
Classifier: Programming Language :: Python
Classifier: Programming Language :: Python :: 3.5
Classifier: Programming Language :: Python :: 3.6
Classifier: Programming Language :: Python :: 3.7
Classifier: Programming Language :: Python :: Implementation :: CPython
Classifier: Topic :: Utilities
